tap_readthedocs/__init__.py
tap_readthedocs/__main__.py
tap_readthedocs/client.py
tap_readthedocs/streams.py
tap_readthedocs/tap.py
tap_readthedocs-0.5.17.dist-info/METADATA
tap_readthedocs-0.5.17.dist-info/WHEEL
tap_readthedocs-0.5.17.dist-info/entry_points.txt
tap_readthedocs-0.5.17.dist-info/licenses/LICENSE
tap_readthedocs-0.5.17.dist-info/RECORD
