Metadata-Version: 2.4
Name: tap-readthedocs
Version: 0.5.17
Summary: Singer tap for ReadTheDocs, built with the Meltano SDK for Singer Taps.
Project-URL: Documentation, https://github.com/reservoir-data/tap-readthedocs#readme
Project-URL: Homepage, https://github.com/reservoir-data/tap-readthedocs
Project-URL: Repository, https://github.com/reservoir-data/tap-readthedocs
Author-email: Edgar Ramírez-Mondragón <edgarrm358@gmail.com>
Maintainer-email: Edgar Ramírez-Mondragón <edgarrm358@gmail.com>
License-Expression: Apache-2.0
License-File: LICENSE
Keywords: ELT,ReadTheDocs,singer.io
Classifier: Programming Language :: Python :: 3 :: Only
Classifier: Programming Language :: Python :: 3.10
Classifier: Programming Language :: Python :: 3.11
Classifier: Programming Language :: Python :: 3.12
Classifier: Programming Language :: Python :: 3.13
Classifier: Programming Language :: Python :: 3.14
Requires-Python: >=3.10
Requires-Dist: requests-cache~=1.0
Requires-Dist: singer-sdk~=0.53.2
Requires-Dist: toolz~=1.1.0
Requires-Dist: typing-extensions>=4.15; python_full_version < '3.12'
